kyle/__init__.py
kyle-0.0.3.dist-info/DESCRIPTION.rst
kyle-0.0.3.dist-info/METADATA
kyle-0.0.3.dist-info/RECORD
kyle-0.0.3.dist-info/WHEEL
kyle-0.0.3.dist-info/metadata.json
kyle-0.0.3.dist-info/top_level.txt
