Metadata-Version: 2.0
Name: kyle
Version: 0.0.3
Summary: Kyle the Python module
Home-page: http://github.com/rgbkrk/kyle
Author: Kyle Kelley
Author-email: rgbkrk@gmail.com
License: Apache License
